json_schema/__init__.py
json_schema/json_differ.py
json_schema/json_schema.py
json_schema/validators.py
json_schema_matcher-0.1.7.1.dist-info/DESCRIPTION.rst
json_schema_matcher-0.1.7.1.dist-info/METADATA
json_schema_matcher-0.1.7.1.dist-info/RECORD
json_schema_matcher-0.1.7.1.dist-info/WHEEL
json_schema_matcher-0.1.7.1.dist-info/metadata.json
json_schema_matcher-0.1.7.1.dist-info/top_level.txt
