Metadata-Version: 1.1
Name: json-schema-matcher
Version: 0.1.7.1
Summary: Use this Lib to create a structure schema of a given JSON and also to check if a given JSON matches a given schema.
Home-page: https://github.com/nano-labs/json_schema
Author: Fabio Pachelli Pacheco
Author-email: nanook.labs@gmail.com
License: MIT
Download-URL: https://github.com/nano-labs/json_schema/archive/release/0.1.7.1.zip
Keywords: json schema diff differ comparison
Platform: UNKNOWN
Classifier: Development Status :: 3 - Alpha
Classifier: Intended Audience :: Developers
Classifier: Topic :: Software Development :: Build Tools
Classifier: License :: OSI Approved :: MIT License
Classifier: Programming Language :: Python :: 3.5
